{
  "project_info": {
    "project_number": "77795768094",
    "project_id": "aplicacioncontactos-8b749",
    "storage_bucket": "aplicacioncontactos-8b749.firebasestorage.app"
  },
  "client": [
    {
      "client_info": {
        "mobilesdk_app_id": "1:77795768094:android:3c29ed1e844460db94bb0f",
        "android_client_info": {
          "package_name": "com.example.helloandroid"
        }
      },
      "oauth_client": [],
      "api_key": [
        {
          "current_key": "AIzaSyAel_3kPg0DjXu8mcoVxOLuWzoGVmYgDfs"
        }
      ],
      "services": {
        "appinvite_service": {
          "other_platform_oauth_client": []
        }
      }
    }
  ],
  "configuration_version": "1"
}